{"CN": {"n": 819976, "media": 468.5, "mediana": 463.3, "std": 64.8, "min": 0.0, "q1": 417.0, "q3": 515.2, "max": 840.2, "hist": [0.0, 16.4, 51.9, 29.3, 2.4, 0.0]}, "CH": {"n": 819976, "media": 486.6, "mediana": 490.4, "std": 79.8, "min": 0.0, "q1": 430.9, "q3": 544.4, "max": 819.7, "hist": [0.1, 14.8, 39.5, 38.9, 6.7, 0.0]}, "LC": {"n": 819976, "media": 507.7, "mediana": 515.5, "std": 62.8, "min": 0.0, "q1": 471.0, "q3": 551.9, "max": 749.1, "hist": [0.0, 6.4, 33.4, 55.6, 4.5, 0.0]}, "MT": {"n": 819976, "media": 493.0, "mediana": 469.5, "std": 89.9, "min": 0.0, "q1": 420.8, "q3": 550.5, "max": 961.9, "hist": [0.0, 12.7, 48.5, 23.7, 14.9, 0.2]}, "RED": {"n": 819976, "media": 626.6, "mediana": 620.0, "std": 156.2, "min": 40.0, "q1": 520.0, "q3": 740.0, "max": 980.0, "hist": [0.1, 6.3, 13.4, 22.3, 40.3, 17.7]}}